{"codes":[{"phenomena1From":"14","phenomena1To":"01","windDir1From":4,"windDir1To":4,"windPow1From":1,"windPow1To":1,"phenomena2From":"02","phenomena2To":"14","windDir2From":4,"windDir2To":4,"windPow2From":1,"windPow2To":1,"phenomena3From":"14","phenomena3To":"01","windDir3From":8,"windDir3To":8,"windPow3From":1,"windPow3To":1,"phenomena4From":"00","phenomena4To":"00","windDir4From":8,"windDir4To":8,"windPow4From":2,"windPow4To":1,"phenomena5From":"00","phenomena5To":"00","windDir5From":8,"windDir5To":8,"windPow5From":2,"windPow5To":1,"phenomena6From":"00","phenomena6To":"00","windDir6From":8,"windDir6To":8,"windPow6From":2,"windPow6To":1,"phenomena7From":"00","phenomena7To":"00","windDir7From":8,"windDir7To":8,"windPow7From":2,"windPow7To":1,"stationName":"石嘴山","stationId":3964,"stationNo":"53518","temp1From":-11,"temp1To":-119,"temp2From":-8,"temp2To":-106,"temp3From":-52,"temp3To":-136,"temp4From":-40,"temp4To":-179,"temp5From":-21,"temp5To":-190,"temp6From":-25,"temp6To":-174,"temp7From":-24,"temp7To":-153,"id":63666},{"phenomena1From":"14","phenomena1To":"01","windDir1From":4,"windDir1To":4,"windPow1From":1,"windPow1To":1,"phenomena2From":"02","phenomena2To":"14","windDir2From":4,"windDir2To":4,"windPow2From":1,"windPow2To":1,"phenomena3From":"14","phenomena3To":"01","windDir3From":8,"windDir3To":8,"windPow3From":1,"windPow3To":1,"phenomena4From":"00","phenomena4To":"00","windDir4From":8,"windDir4To":8,"windPow4From":2,"windPow4To":1,"phenomena5From":"00","phenomena5To":"00","windDir5From":8,"windDir5To":8,"windPow5From":2,"windPow5To":1,"phenomena6From":"00","phenomena6To":"00","windDir6From":8,"windDir6To":8,"windPow6From":2,"windPow6To":1,"phenomena7From":"00","phenomena7To":"00","windDir7From":8,"windDir7To":8,"windPow7From":2,"windPow7To":1,"stationName":"惠农","stationId":3965,"stationNo":"53519","temp1From":-4,"temp1To":-89,"temp2From":2,"temp2To":-78,"temp3From":-47,"temp3To":-116,"temp4From":-78,"temp4To":-153,"temp5From":-48,"temp5To":-148,"temp6From":-7,"temp6To":-144,"temp7From":-2,"temp7To":-113,"id":63667},{"phenomena1From":"14","phenomena1To":"01","windDir1From":4,"windDir1To":4,"windPow1From":1,"windPow1To":1,"phenomena2From":"02","phenomena2To":"14","windDir2From":4,"windDir2To":4,"windPow2From":1,"windPow2To":1,"phenomena3From":"14","phenomena3To":"01","windDir3From":8,"windDir3To":8,"windPow3From":1,"windPow3To":1,"phenomena4From":"00","phenomena4To":"00","windDir4From":8,"windDir4To":8,"windPow4From":2,"windPow4To":1,"phenomena5From":"00","phenomena5To":"00","windDir5From":8,"windDir5To":8,"windPow5From":2,"windPow5To":1,"phenomena6From":"00","phenomena6To":"00","windDir6From":8,"windDir6To":8,"windPow6From":2,"windPow6To":1,"phenomena7From":"00","phenomena7To":"00","windDir7From":8,"windDir7To":8,"windPow7From":2,"windPow7To":1,"stationName":"平罗","stationId":3970,"stationNo":"53611","temp1From":-6,"temp1To":-113,"temp2From":-4,"temp2To":-106,"temp3From":-38,"temp3To":-140,"temp4From":-56,"temp4To":-170,"temp5From":-18,"temp5To":-167,"temp6From":-8,"temp6To":-141,"temp7From":-10,"temp7To":-125,"id":63668},{"phenomena1From":"14","phenomena1To":"01","windDir1From":4,"windDir1To":4,"windPow1From":1,"windPow1To":1,"phenomena2From":"02","phenomena2To":"14","windDir2From":4,"windDir2To":4,"windPow2From":1,"windPow2To":1,"phenomena3From":"14","phenomena3To":"01","windDir3From":8,"windDir3To":8,"windPow3From":1,"windPow3To":1,"phenomena4From":"00","phenomena4To":"00","windDir4From":8,"windDir4To":8,"windPow4From":2,"windPow4To":1,"phenomena5From":"00","phenomena5To":"00","windDir5From":8,"windDir5To":8,"windPow5From":2,"windPow5To":1,"phenomena6From":"00","phenomena6To":"00","windDir6From":8,"windDir6To":8,"windPow6From":2,"windPow6To":1,"phenomena7From":"00","phenomena7To":"00","windDir7From":8,"windDir7To":8,"windPow7From":2,"windPow7To":1,"stationName":"陶乐","stationId":3973,"stationNo":"53615","temp1From":-16,"temp1To":-100,"temp2From":13,"temp2To":-108,"temp3From":-45,"temp3To":-148,"temp4From":-63,"temp4To":-188,"temp5From":-25,"temp5To":-177,"temp6From":2,"temp6To":-170,"temp7From":4,"temp7To":-150,"id":63669},{"phenomena1From":"14","phenomena1To":"01","windDir1From":4,"windDir1To":4,"windPow1From":1,"windPow1To":1,"phenomena2From":"02","phenomena2To":"14","windDir2From":4,"windDir2To":4,"windPow2From":1,"windPow2To":1,"phenomena3From":"14","phenomena3To":"01","windDir3From":8,"windDir3To":8,"windPow3From":1,"windPow3To":1,"phenomena4From":"00","phenomena4To":"00","windDir4From":8,"windDir4To":8,"windPow4From":2,"windPow4To":1,"phenomena5From":"00","phenomena5To":"00","windDir5From":8,"windDir5To":8,"windPow5From":2,"windPow5To":1,"phenomena6From":"00","phenomena6To":"00","windDir6From":8,"windDir6To":8,"windPow6From":2,"windPow6To":1,"phenomena7From":"00","phenomena7To":"00","windDir7From":8,"windDir7To":8,"windPow7From":2,"windPow7To":1,"stationName":"银川","stationId":3972,"stationNo":"53614","temp1From":-15,"temp1To":-92,"temp2From":-11,"temp2To":-98,"temp3From":-31,"temp3To":-116,"temp4From":-40,"temp4To":-157,"temp5From":-15,"temp5To":-146,"temp6From":-8,"temp6To":-125,"temp7From":-13,"temp7To":-114,"id":63670},{"phenomena1From":"14","phenomena1To":"01","windDir1From":4,"windDir1To":4,"windPow1From":1,"windPow1To":1,"phenomena2From":"02","phenomena2To":"14","windDir2From":4,"windDir2To":4,"windPow2From":1,"windPow2To":1,"phenomena3From":"14","phenomena3To":"01","windDir3From":8,"windDir3To":8,"windPow3From":1,"windPow3To":1,"phenomena4From":"00","phenomena4To":"00","windDir4From":8,"windDir4To":8,"windPow4From":2,"windPow4To":1,"phenomena5From":"00","phenomena5To":"00","windDir5From":8,"windDir5To":8,"windPow5From":2,"windPow5To":1,"phenomena6From":"00","phenomena6To":"00","windDir6From":8,"windDir6To":8,"windPow6From":2,"windPow6To":1,"phenomena7From":"00","phenomena7To":"00","windDir7From":8,"windDir7To":8,"windPow7From":2,"windPow7To":1,"stationName":"贺兰","stationId":3969,"stationNo":"53610","temp1From":-22,"temp1To":-104,"temp2From":-4,"temp2To":-87,"temp3From":-41,"temp3To":-134,"temp4From":-41,"temp4To":-176,"temp5From":-15,"temp5To":-160,"temp6From":7,"temp6To":-154,"temp7From":0,"temp7To":-146,"id":63671},{"phenomena1From":"14","phenomena1To":"01","windDir1From":4,"windDir1To":4,"windPow1From":1,"windPow1To":1,"phenomena2From":"02","phenomena2To":"14","windDir2From":4,"windDir2To":4,"windPow2From":1,"windPow2To":1,"phenomena3From":"02","phenomena3To":"01","windDir3From":8,"windDir3To":8,"windPow3From":1,"windPow3To":1,"phenomena4From":"00","phenomena4To":"00","windDir4From":8,"windDir4To":8,"windPow4From":2,"windPow4To":1,"phenomena5From":"00","phenomena5To":"00","windDir5From":8,"windDir5To":8,"windPow5From":2,"windPow5To":1,"phenomena6From":"00","phenomena6To":"00","windDir6From":8,"windDir6To":8,"windPow6From":2,"windPow6To":1,"phenomena7From":"00","phenomena7To":"00","windDir7From":8,"windDir7To":8,"windPow7From":2,"windPow7To":1,"stationName":"永宁","stationId":3975,"stationNo":"53618","temp1From":0,"temp1To":-93,"temp2From":9,"temp2To":-101,"temp3From":-20,"temp3To":-120,"temp4From":-36,"temp4To":-155,"temp5From":-16,"temp5To":-151,"temp6From":8,"temp6To":-139,"temp7From":5,"temp7To":-123,"id":63672},{"phenomena1From":"14","phenomena1To":"01","windDir1From":4,"windDir1To":4,"windPow1From":1,"windPow1To":1,"phenomena2From":"02","phenomena2To":"14","windDir2From":4,"windDir2To":4,"windPow2From":1,"windPow2To":1,"phenomena3From":"02","phenomena3To":"01","windDir3From":8,"windDir3To":8,"windPow3From":1,"windPow3To":1,"phenomena4From":"00","phenomena4To":"00","windDir4From":8,"windDir4To":8,"windPow4From":2,"windPow4To":1,"phenomena5From":"00","phenomena5To":"00","windDir5From":8,"windDir5To":8,"windPow5From":2,"windPow5To":1,"phenomena6From":"00","phenomena6To":"00","windDir6From":8,"windDir6To":8,"windPow6From":2,"windPow6To":1,"phenomena7From":"00","phenomena7To":"00","windDir7From":8,"windDir7To":8,"windPow7From":2,"windPow7To":1,"stationName":"灵武","stationId":3976,"stationNo":"53619","temp1From":0,"temp1To":-119,"temp2From":1,"temp2To":-94,"temp3From":-44,"temp3To":-130,"temp4From":-35,"temp4To":-180,"temp5From":-4,"temp5To":-154,"temp6From":-11,"temp6To":-157,"temp7From":16,"temp7To":-153,"id":63673},{"phenomena1From":"14","phenomena1To":"01","windDir1From":4,"windDir1To":4,"windPow1From":1,"windPow1To":1,"phenomena2From":"02","phenomena2To":"14","windDir2From":4,"windDir2To":4,"windPow2From":1,"windPow2To":1,"phenomena3From":"02","phenomena3To":"01","windDir3From":8,"windDir3To":8,"windPow3From":1,"windPow3To":1,"phenomena4From":"00","phenomena4To":"00","windDir4From":8,"windDir4To":8,"windPow4From":2,"windPow4To":1,"phenomena5From":"00","phenomena5To":"00","windDir5From":8,"windDir5To":8,"windPow5From":2,"windPow5To":1,"phenomena6From":"00","phenomena6To":"00","windDir6From":8,"windDir6To":8,"windPow6From":2,"windPow6To":1,"phenomena7From":"00","phenomena7To":"00","windDir7From":8,"windDir7To":8,"windPow7From":2,"windPow7To":1,"stationName":"吴忠","stationId":3971,"stationNo":"53612","temp1From":-6,"temp1To":-85,"temp2From":-6,"temp2To":-88,"temp3From":-39,"temp3To":-116,"temp4From":-16,"temp4To":-134,"temp5From":-3,"temp5To":-122,"temp6From":-20,"temp6To":-118,"temp7From":16,"temp7To":-116,"id":63674},{"phenomena1From":"14","phenomena1To":"01","windDir1From":4,"windDir1To":4,"windPow1From":1,"windPow1To":1,"phenomena2From":"02","phenomena2To":"14","windDir2From":4,"windDir2To":4,"windPow2From":1,"windPow2To":1,"phenomena3From":"02","phenomena3To":"01","windDir3From":8,"windDir3To":8,"windPow3From":1,"windPow3To":1,"phenomena4From":"00","phenomena4To":"00","windDir4From":8,"windDir4To":8,"windPow4From":2,"windPow4To":1,"phenomena5From":"00","phenomena5To":"00","windDir5From":8,"windDir5To":8,"windPow5From":2,"windPow5To":1,"phenomena6From":"00","phenomena6To":"00","windDir6From":8,"windDir6To":8,"windPow6From":2,"windPow6To":1,"phenomena7From":"00","phenomena7To":"00","windDir7From":8,"windDir7To":8,"windPow7From":2,"windPow7To":1,"stationName":"青铜峡","stationId":3974,"stationNo":"53617","temp1From":-16,"temp1To":-92,"temp2From":-10,"temp2To":-83,"temp3From":-35,"temp3To":-119,"temp4From":-24,"temp4To":-142,"temp5From":-9,"temp5To":-141,"temp6From":4,"temp6To":-138,"temp7From":-2,"temp7To":-124,"id":63675},{"phenomena1From":"02","phenomena1To":"01","windDir1From":4,"windDir1To":4,"windPow1From":1,"windPow1To":1,"phenomena2From":"02","phenomena2To":"14","windDir2From":4,"windDir2To":4,"windPow2From":1,"windPow2To":1,"phenomena3From":"02","phenomena3To":"01","windDir3From":8,"windDir3To":8,"windPow3From":1,"windPow3To":1,"phenomena4From":"00","phenomena4To":"00","windDir4From":8,"windDir4To":8,"windPow4From":2,"windPow4To":1,"phenomena5From":"00","phenomena5To":"00","windDir5From":8,"windDir5To":8,"windPow5From":2,"windPow5To":1,"phenomena6From":"00","phenomena6To":"00","windDir6From":8,"windDir6To":8,"windPow6From":2,"windPow6To":1,"phenomena7From":"00","phenomena7To":"00","windDir7From":8,"windDir7To":8,"windPow7From":2,"windPow7To":1,"stationName":"盐池","stationId":3983,"stationNo":"53723","temp1From":-20,"temp1To":-125,"temp2From":-28,"temp2To":-98,"temp3From":-47,"temp3To":-155,"temp4From":-51,"temp4To":-179,"temp5From":-34,"temp5To":-160,"temp6From":-20,"temp6To":-166,"temp7From":-2,"temp7To":-168,"id":63676},{"phenomena1From":"02","phenomena1To":"01","windDir1From":4,"windDir1To":4,"windPow1From":1,"windPow1To":1,"phenomena2From":"02","phenomena2To":"14","windDir2From":4,"windDir2To":4,"windPow2From":1,"windPow2To":1,"phenomena3From":"02","phenomena3To":"01","windDir3From":8,"windDir3To":8,"windPow3From":1,"windPow3To":1,"phenomena4From":"00","phenomena4To":"00","windDir4From":8,"windDir4To":8,"windPow4From":2,"windPow4To":1,"phenomena5From":"00","phenomena5To":"00","windDir5From":8,"windDir5To":8,"windPow5From":2,"windPow5To":1,"phenomena6From":"00","phenomena6To":"00","windDir6From":8,"windDir6To":8,"windPow6From":2,"windPow6To":1,"phenomena7From":"00","phenomena7To":"00","windDir7From":8,"windDir7To":8,"windPow7From":2,"windPow7To":1,"stationName":"同心","stationId":3987,"stationNo":"53810","temp1From":10,"temp1To":-94,"temp2From":-9,"temp2To":-111,"temp3From":-56,"temp3To":-143,"temp4From":-23,"temp4To":-146,"temp5From":-17,"temp5To":-145,"temp6From":13,"temp6To":-138,"temp7From":18,"temp7To":-129,"id":63677},{"phenomena1From":"02","phenomena1To":"01","windDir1From":4,"windDir1To":4,"windPow1From":1,"windPow1To":1,"phenomena2From":"02","phenomena2To":"14","windDir2From":4,"windDir2To":4,"windPow2From":1,"windPow2To":1,"phenomena3From":"02","phenomena3To":"01","windDir3From":8,"windDir3To":8,"windPow3From":1,"windPow3To":1,"phenomena4From":"00","phenomena4To":"00","windDir4From":8,"windDir4To":8,"windPow4From":2,"windPow4To":1,"phenomena5From":"00","phenomena5To":"00","windDir5From":8,"windDir5To":8,"windPow5From":2,"windPow5To":1,"phenomena6From":"00","phenomena6To":"00","windDir6From":8,"windDir6To":8,"windPow6From":2,"windPow6To":1,"phenomena7From":"00","phenomena7To":"00","windDir7From":8,"windDir7To":8,"windPow7From":2,"windPow7To":1,"stationName":"中卫","stationId":3977,"stationNo":"53704","temp1From":10,"temp1To":-89,"temp2From":-8,"temp2To":-97,"temp3From":-40,"temp3To":-133,"temp4From":-28,"temp4To":-142,"temp5From":6,"temp5To":-139,"temp6From":-5,"temp6To":-133,"temp7From":0,"temp7To":-133,"id":63678},{"phenomena1From":"02","phenomena1To":"01","windDir1From":4,"windDir1To":4,"windPow1From":1,"windPow1To":1,"phenomena2From":"02","phenomena2To":"14","windDir2From":4,"windDir2To":4,"windPow2From":1,"windPow2To":1,"phenomena3From":"02","phenomena3To":"01","windDir3From":8,"windDir3To":8,"windPow3From":1,"windPow3To":1,"phenomena4From":"00","phenomena4To":"00","windDir4From":8,"windDir4To":8,"windPow4From":2,"windPow4To":1,"phenomena5From":"00","phenomena5To":"00","windDir5From":8,"windDir5To":8,"windPow5From":2,"windPow5To":1,"phenomena6From":"00","phenomena6To":"00","windDir6From":8,"windDir6To":8,"windPow6From":2,"windPow6To":1,"phenomena7From":"00","phenomena7To":"00","windDir7From":8,"windDir7To":8,"windPow7From":2,"windPow7To":1,"stationName":"中宁","stationId":3978,"stationNo":"53705","temp1From":-6,"temp1To":-81,"temp2From":-7,"temp2To":-96,"temp3From":-25,"temp3To":-121,"temp4From":-13,"temp4To":-150,"temp5From":7,"temp5To":-115,"temp6From":4,"temp6To":-106,"temp7From":8,"temp7To":-127,"id":63679},{"phenomena1From":"02","phenomena1To":"01","windDir1From":4,"windDir1To":4,"windPow1From":1,"windPow1To":1,"phenomena2From":"02","phenomena2To":"14","windDir2From":4,"windDir2To":4,"windPow2From":1,"windPow2To":1,"phenomena3From":"02","phenomena3To":"01","windDir3From":8,"windDir3To":8,"windPow3From":1,"windPow3To":1,"phenomena4From":"00","phenomena4To":"00","windDir4From":8,"windDir4To":8,"windPow4From":2,"windPow4To":1,"phenomena5From":"00","phenomena5To":"00","windDir5From":8,"windDir5To":8,"windPow5From":2,"windPow5To":1,"phenomena6From":"00","phenomena6To":"00","windDir6From":8,"windDir6To":8,"windPow6From":2,"windPow6To":1,"phenomena7From":"00","phenomena7To":"00","windDir7From":8,"windDir7To":8,"windPow7From":2,"windPow7To":1,"stationName":"海原","stationId":3986,"stationNo":"53806","temp1From":-6,"temp1To":-93,"temp2From":-26,"temp2To":-106,"temp3From":-64,"temp3To":-144,"temp4From":-50,"temp4To":-135,"temp5From":-39,"temp5To":-122,"temp6From":1,"temp6To":-105,"temp7From":13,"temp7To":-103,"id":63680},{"phenomena1From":"02","phenomena1To":"01","windDir1From":4,"windDir1To":4,"windPow1From":1,"windPow1To":1,"phenomena2From":"02","phenomena2To":"14","windDir2From":4,"windDir2To":4,"windPow2From":1,"windPow2To":1,"phenomena3From":"14","phenomena3To":"01","windDir3From":8,"windDir3To":8,"windPow3From":1,"windPow3To":1,"phenomena4From":"00","phenomena4To":"00","windDir4From":8,"windDir4To":8,"windPow4From":2,"windPow4To":1,"phenomena5From":"00","phenomena5To":"00","windDir5From":8,"windDir5To":8,"windPow5From":2,"windPow5To":1,"phenomena6From":"00","phenomena6To":"00","windDir6From":8,"windDir6To":8,"windPow6From":2,"windPow6To":1,"phenomena7From":"00","phenomena7To":"01","windDir7From":8,"windDir7To":8,"windPow7From":2,"windPow7To":1,"stationName":"固原","stationId":3990,"stationNo":"53817","temp1From":-15,"temp1To":-92,"temp2From":-26,"temp2To":-96,"temp3From":-67,"temp3To":-140,"temp4From":-59,"temp4To":-143,"temp5From":-1,"temp5To":-133,"temp6From":1,"temp6To":-119,"temp7From":21,"temp7To":-117,"id":63681},{"phenomena1From":"02","phenomena1To":"01","windDir1From":4,"windDir1To":4,"windPow1From":1,"windPow1To":1,"phenomena2From":"02","phenomena2To":"14","windDir2From":4,"windDir2To":4,"windPow2From":1,"windPow2To":1,"phenomena3From":"02","phenomena3To":"01","windDir3From":8,"windDir3To":8,"windPow3From":1,"windPow3To":1,"phenomena4From":"00","phenomena4To":"00","windDir4From":8,"windDir4To":8,"windPow4From":2,"windPow4To":1,"phenomena5From":"00","phenomena5To":"00","windDir5From":8,"windDir5To":8,"windPow5From":2,"windPow5To":1,"phenomena6From":"00","phenomena6To":"00","windDir6From":8,"windDir6To":8,"windPow6From":2,"windPow6To":1,"phenomena7From":"00","phenomena7To":"01","windDir7From":8,"windDir7To":8,"windPow7From":2,"windPow7To":1,"stationName":"西吉","stationId":3994,"stationNo":"53903","temp1From":-9,"temp1To":-109,"temp2From":0,"temp2To":-113,"temp3From":-60,"temp3To":-178,"temp4From":-58,"temp4To":-180,"temp5From":-15,"temp5To":-190,"temp6From":-6,"temp6To":-171,"temp7From":-8,"temp7To":-166,"id":63682},{"phenomena1From":"02","phenomena1To":"01","windDir1From":4,"windDir1To":4,"windPow1From":1,"windPow1To":1,"phenomena2From":"02","phenomena2To":"14","windDir2From":4,"windDir2To":4,"windPow2From":1,"windPow2To":1,"phenomena3From":"14","phenomena3To":"01","windDir3From":8,"windDir3To":8,"windPow3From":1,"windPow3To":1,"phenomena4From":"00","phenomena4To":"00","windDir4From":8,"windDir4To":8,"windPow4From":2,"windPow4To":1,"phenomena5From":"00","phenomena5To":"00","windDir5From":8,"windDir5To":8,"windPow5From":2,"windPow5To":1,"phenomena6From":"00","phenomena6To":"00","windDir6From":8,"windDir6To":8,"windPow6From":2,"windPow6To":1,"phenomena7From":"00","phenomena7To":"01","windDir7From":8,"windDir7To":8,"windPow7From":2,"windPow7To":1,"stationName":"隆德","stationId":3997,"stationNo":"53914","temp1From":-13,"temp1To":-98,"temp2From":-25,"temp2To":-106,"temp3From":-71,"temp3To":-158,"temp4From":-62,"temp4To":-163,"temp5From":-49,"temp5To":-167,"temp6From":-16,"temp6To":-145,"temp7From":-14,"temp7To":-144,"id":63683},{"phenomena1From":"02","phenomena1To":"01","windDir1From":4,"windDir1To":4,"windPow1From":1,"windPow1To":1,"phenomena2From":"14","phenomena2To":"14","windDir2From":4,"windDir2To":4,"windPow2From":1,"windPow2To":1,"phenomena3From":"14","phenomena3To":"01","windDir3From":8,"windDir3To":8,"windPow3From":1,"windPow3To":1,"phenomena4From":"00","phenomena4To":"00","windDir4From":8,"windDir4To":8,"windPow4From":2,"windPow4To":1,"phenomena5From":"00","phenomena5To":"00","windDir5From":8,"windDir5To":8,"windPow5From":2,"windPow5To":1,"phenomena6From":"00","phenomena6To":"00","windDir6From":8,"windDir6To":8,"windPow6From":2,"windPow6To":1,"phenomena7From":"00","phenomena7To":"01","windDir7From":8,"windDir7To":8,"windPow7From":2,"windPow7To":1,"stationName":"泾源","stationId":3998,"stationNo":"53916","temp1From":-30,"temp1To":-102,"temp2From":-26,"temp2To":-108,"temp3From":-73,"temp3To":-130,"temp4From":-13,"temp4To":-146,"temp5From":-12,"temp5To":-133,"temp6From":4,"temp6To":-130,"temp7From":13,"temp7To":-128,"id":63684},{"phenomena1From":"02","phenomena1To":"01","windDir1From":4,"windDir1To":4,"windPow1From":1,"windPow1To":1,"phenomena2From":"02","phenomena2To":"14","windDir2From":4,"windDir2To":4,"windPow2From":1,"windPow2To":1,"phenomena3From":"14","phenomena3To":"01","windDir3From":8,"windDir3To":8,"windPow3From":1,"windPow3To":1,"phenomena4From":"00","phenomena4To":"00","windDir4From":8,"windDir4To":8,"windPow4From":2,"windPow4To":1,"phenomena5From":"00","phenomena5To":"00","windDir5From":8,"windDir5To":8,"windPow5From":2,"windPow5To":1,"phenomena6From":"00","phenomena6To":"00","windDir6From":8,"windDir6To":8,"windPow6From":2,"windPow6To":1,"phenomena7From":"00","phenomena7To":"01","windDir7From":8,"windDir7To":8,"windPow7From":2,"windPow7To":1,"stationName":"彭阳","stationId":3996,"stationNo":"53913","temp1From":-27,"temp1To":-93,"temp2From":-17,"temp2To":-86,"temp3From":-47,"temp3To":-150,"temp4From":-18,"temp4To":-160,"temp5From":11,"temp5To":-151,"temp6From":18,"temp6To":-103,"temp7From":62,"temp7To":-131,"id":63685}],"info":{"timeType":10,"createBy":"何劲夫","updateBy":null,"fixStatus":null,"updateTime":null,"createTime":1515027307693,"partSendCount":0,"shortCreateBy":"何劲夫","shortCount":20,"mediumCount":20,"sendCount":1,"tempRadix":10,"principal":"陈豫英","status":"YF","id":3166}}